{
    "data": {
        "train": "train_m",
        "dev": [
            "dev"
        ],
        "test": [
            "aishell-test"
        ],
        "filter": ":1000",
        "lang": "zh-cn"
    },
    "tokenizer": {
        "type": "SentencePieceTokenizer",
        "property": {
            "model_type": "char",
            "add_dummy_prefix": false,
            "use_all_vocab": true,
            "model_prefix": "sentencepiece/wenetspeech_char/spm",
            "vocab_size": 5147
        },
        "location": "exp/rnnt/rnnt-v1/tokenizer.tknz"
    },
    "train": {
        "batch_size": 512,
        "grad-norm": 5.0,
        "databalance": true,
        "checkall": true,
        "amp": true
    },
    "inference": {
        "avgmodel": {
            "mode": "best",
            "num": 10
        },
        "lmdir": "exp/lm/lm-aishell",
        "decode": {
            "algo": "rna",
            "beam-size": 16,
            "alpha": 0.5,
            "beta": 1.2,
            "ilm-weight": -0.12,
            "cpu": true,
            "nj": 20,
            "resume": "exp/rnnt/rnnt-v1/checks/best-10.pt"
        },
        "er": {
            "mode": "cer",
            "oracle": false
        }
    },
    "commit": "7646b5581cd08ae1058d6e9cfceec4ffaad68fe8"
}